{
  "users": [
    {
      "id": 1,
      "FullName": "Amanda Hicks",
      "account": "companydomain/AmandaHicks",
      "mail": "of7872230@companydomain.com",
      "groop": "Unmanaged",
      "number": "+75063599041"
    },
    {
      "id": 2,
      "FullName": "Karen Vega",
      "account": "companydomain/KarenVega",
      "mail": "of6766051@companydomain.com",
      "groop": "CDN/Financials",
      "number": "+77026275600"
    },
    {
      "id": 3,
      "FullName": "Ella Ginn",
      "account": "companydomain/EllaGinn",
      "mail": "turtle4827407@companydomain.com",
      "groop": "CDN/Managers",
      "number": "+72709216541"
    },
    {
      "id": 4,
      "FullName": "Dorothy Begay",
      "account": "companydomain/DorothyBegay",
      "mail": "starfish9639824@companydomain.com",
      "groop": "CDN/Human resources",
      "number": "+77232071286"
    },
    {
      "id": 5,
      "FullName": "William Hughes",
      "account": "companydomain/WilliamHughes",
      "mail": "realistic9221498@companydomain.com",
      "groop": "CDN/Top Kvants",
      "number": "+78205424117"
    },
    {
      "id": 6,
      "FullName": "Pedro Wolter",
      "account": "companydomain/PedroWolter",
      "mail": "bright3851647@companydomain.com",
      "groop": "CDN/CEO",
      "number": "+79492090626"
    },
    {
      "id": 7,
      "FullName": "Tiffany Pryor",
      "account": "companydomain/TiffanyPryor",
      "mail": "interesting7803587@companydomain.com",
      "groop": "CDN/Financials",
      "number": "+75261690416"
    },
    {
      "id": 8,
      "FullName": "Edward Burris",
      "account": "companydomain/EdwardBurris",
      "mail": "crouching9999200@companydomain.com",
      "groop": "CDN/Managers",
      "number": "+74245373622"
    },
    {
      "id": 9,
      "FullName": "Sandra Torres",
      "account": "companydomain/SandraTorres",
      "mail": "splendid5805508@companydomain.com",
      "groop": "CDN/Managers",
      "number": "+75521075492"
    },
    {
      "id": 10,
      "FullName": "Leonard Welch",
      "account": "companydomain/LeonardWelch",
      "mail": "buffalo2515609@companydomain.com",
      "groop": "CDN/Financials",
      "number": "+77533854723"
    },
    {
      "id": 11,
      "FullName": "Jason Puckett",
      "account": "companydomain/JasonPuckett",
      "mail": "cricket2389033@companydomain.com",
      "groop": "CDN/Top Kvants",
      "number": "+73854449272"
    },
    {
      "id": 12,
      "FullName": "Carmen Pinkney",
      "account": "companydomain/CarmenPinkney",
      "mail": "rain7468017@companydomain.com",
      "groop": "CDN/Managers",
      "number": "+76259508961"
    },
    {
      "id": 13,
      "FullName": "Suzanne Rasmussen",
      "account": "companydomain/SuzanneRasmussen",
      "mail": "trout6579748@companydomain.com",
      "groop": "CDN/Financials",
      "number": "+71284162897"
    },
    {
      "id": 14,
      "FullName": "Richard Mcdonell",
      "account": "companydomain/RichardMcdonell",
      "mail": "realization6088194@companydomain.com",
      "groop": "CDN/Sales",
      "number": "+77459083785"
    },
    {
      "id": 15,
      "FullName": "Julie Thomas",
      "account": "companydomain/JulieThomas",
      "mail": "chameleon701463@companydomain.com",
      "groop": "Unmanaged",
      "number": "+79974115426"
    },
    {
      "id": 16,
      "FullName": "Elizabeth Anker",
      "account": "companydomain/ElizabethAnker",
      "mail": "nippy7387773@companydomain.com",
      "groop": "CDN/Human resources",
      "number": "+73769736328"
    },
    {
      "id": 17,
      "FullName": "Marilyn Mcgirt",
      "account": "companydomain/MarilynMcgirt",
      "mail": "pluto8221380@companydomain.com",
      "groop": "CDN/CEO",
      "number": "+75222178160"
    },
    {
      "id": 18,
      "FullName": "Clyde Arms",
      "account": "companydomain/ClydeArms",
      "mail": "meek5971673@companydomain.com",
      "groop": "Unmanaged",
      "number": "+73341703071"
    },
    {
      "id": 19,
      "FullName": "Donn White",
      "account": "companydomain/DonnWhite",
      "mail": "of9002865@companydomain.com",
      "groop": "CDN/Managers",
      "number": "+73558114562"
    },
    {
      "id": 20,
      "FullName": "Emile Hall",
      "account": "companydomain/EmileHall",
      "mail": "serval7931187@companydomain.com",
      "groop": "CDN/CEO",
      "number": "+71640825452"
    },
    {
      "id": 21,
      "FullName": "Linda Zuniga",
      "account": "companydomain/LindaZuniga",
      "mail": "eager2321552@companydomain.com",
      "groop": "CDN/Managers",
      "number": "+78862907763"
    },
    {
      "id": 22,
      "FullName": "James Marvin",
      "account": "companydomain/JamesMarvin",
      "mail": "tacky9892106@companydomain.com",
      "groop": "CDN/Human resources",
      "number": "+79481902001"
    },
    {
      "id": 23,
      "FullName": "Celia Smith",
      "account": "companydomain/CeliaSmith",
      "mail": "lemming77526@companydomain.com",
      "groop": "CDN/CEO",
      "number": "+77089302777"
    },
    {
      "id": 24,
      "FullName": "Doris Shelby",
      "account": "companydomain/DorisShelby",
      "mail": "ginger6112335@companydomain.com",
      "groop": "CDN/Top Kvants",
      "number": "+74402526475"
    },
    {
      "id": 25,
      "FullName": "Rosie Mattson",
      "account": "companydomain/RosieMattson",
      "mail": "of881781@companydomain.com",
      "groop": "Unmanaged",
      "number": "+73995147559"
    },
    {
      "id": 26,
      "FullName": "Michael Pringle",
      "account": "companydomain/MichaelPringle",
      "mail": "wealth8229605@companydomain.com",
      "groop": "Unmanaged",
      "number": "+75833598418"
    },
    {
      "id": 27,
      "FullName": "Robert Lister",
      "account": "companydomain/RobertLister",
      "mail": "amusing656355@companydomain.com",
      "groop": "Unmanaged",
      "number": "+79753974876"
    },
    {
      "id": 28,
      "FullName": "Ronald Benett",
      "account": "companydomain/RonaldBenett",
      "mail": "oarfish6562360@companydomain.com",
      "groop": "CDN/Human resources",
      "number": "+72631250271"
    },
    {
      "id": 29,
      "FullName": "Darla Vegetabile",
      "account": "companydomain/DarlaVegetabile",
      "mail": "porpoise6381586@companydomain.com",
      "groop": "CDN/Human resources",
      "number": "+72657012580"
    },
    {
      "id": 30,
      "FullName": "Inez Olson",
      "account": "companydomain/InezOlson",
      "mail": "modernism1410488@companydomain.com",
      "groop": "CDN/Managers",
      "number": "+71853262404"
    },
    {
      "id": 31,
      "FullName": "Amanda Goodrich",
      "account": "companydomain/AmandaGoodrich",
      "mail": "vegan3863387@companydomain.com",
      "groop": "CDN/CEO",
      "number": "+79912432957"
    },
    {
      "id": 32,
      "FullName": "Pamela Miller",
      "account": "companydomain/PamelaMiller",
      "mail": "mule7497836@companydomain.com",
      "groop": "CDN/Managers",
      "number": "+76403609037"
    },
    {
      "id": 33,
      "FullName": "Deborah Magnuson",
      "account": "companydomain/DeborahMagnuson",
      "mail": "kangaroo5288784@companydomain.com",
      "groop": "CDN/Financials",
      "number": "+73462592532"
    },
    {
      "id": 34,
      "FullName": "Alexander Toscano",
      "account": "companydomain/AlexanderToscano",
      "mail": "weightless2908628@companydomain.com",
      "groop": "CDN/Sales",
      "number": "+77295724554"
    },
    {
      "id": 35,
      "FullName": "Janet Sim",
      "account": "companydomain/JanetSim",
      "mail": "of9070479@companydomain.com",
      "groop": "CDN/Top Kvants",
      "number": "+79991077058"
    },
    {
      "id": 36,
      "FullName": "Miguelina Burnside",
      "account": "companydomain/MiguelinaBurnside",
      "mail": "of2354755@companydomain.com",
      "groop": "CDN/CEO",
      "number": "+79132220095"
    },
    {
      "id": 37,
      "FullName": "Garland Fett",
      "account": "companydomain/GarlandFett",
      "mail": "mayfly6453149@companydomain.com",
      "groop": "CDN/Human resources",
      "number": "+74836516393"
    },
    {
      "id": 38,
      "FullName": "Zenia Mowery",
      "account": "companydomain/ZeniaMowery",
      "mail": "puma8087606@companydomain.com",
      "groop": "CDN/CEO",
      "number": "+78689519982"
    },
    {
      "id": 39,
      "FullName": "Barbara Buzzelli",
      "account": "companydomain/BarbaraBuzzelli",
      "mail": "venus4644506@companydomain.com",
      "groop": "CDN/Managers",
      "number": "+79925710546"
    },
    {
      "id": 40,
      "FullName": "Dawn Bradshaw",
      "account": "companydomain/DawnBradshaw",
      "mail": "endeavor3783426@companydomain.com",
      "groop": "CDN/Managers",
      "number": "+74252232915"
    },
    {
      "id": 41,
      "FullName": "Anna Bruhn",
      "account": "companydomain/AnnaBruhn",
      "mail": "nebulous314852@companydomain.com",
      "groop": "CDN/Top Kvants",
      "number": "+72110923451"
    },
    {
      "id": 42,
      "FullName": "Jacque Medcalf",
      "account": "companydomain/JacqueMedcalf",
      "mail": "of4177474@companydomain.com",
      "groop": "CDN/Sales",
      "number": "+79138438620"
    },
    {
      "id": 43,
      "FullName": "Alan Dente",
      "account": "companydomain/AlanDente",
      "mail": "koala4356633@companydomain.com",
      "groop": "CDN/Sales",
      "number": "+76580504209"
    },
    {
      "id": 44,
      "FullName": "Helen Christiansen",
      "account": "companydomain/HelenChristiansen",
      "mail": "pluto2605696@companydomain.com",
      "groop": "CDN/Managers",
      "number": "+76051857076"
    },
    {
      "id": 45,
      "FullName": "Michelle Campbell",
      "account": "companydomain/MichelleCampbell",
      "mail": "determined8066967@companydomain.com",
      "groop": "CDN/Human resources",
      "number": "+78508228485"
    },
    {
      "id": 46,
      "FullName": "Micheal Achee",
      "account": "companydomain/MichealAchee",
      "mail": "aptitude5493642@companydomain.com",
      "groop": "CDN/CEO",
      "number": "+73551492101"
    },
    {
      "id": 47,
      "FullName": "Kelly Owings",
      "account": "companydomain/KellyOwings",
      "mail": "of4908803@companydomain.com",
      "groop": "CDN/Top Kvants",
      "number": "+76357538706"
    },
    {
      "id": 48,
      "FullName": "Javier Gulledge",
      "account": "companydomain/JavierGulledge",
      "mail": "politeness7071275@companydomain.com",
      "groop": "CDN/Managers",
      "number": "+77575172710"
    },
    {
      "id": 49,
      "FullName": "Marlene Baker",
      "account": "companydomain/MarleneBaker",
      "mail": "of7862360@companydomain.com",
      "groop": "CDN/Sales",
      "number": "+72326684557"
    },
    {
      "id": 50,
      "FullName": "William Tomas",
      "account": "companydomain/WilliamTomas",
      "mail": "of5936993@companydomain.com",
      "groop": "CDN/CEO",
      "number": "+73660651749"
    },
    {
      "id": 51,
      "FullName": "Sheryl Parsons",
      "account": "companydomain/SherylParsons",
      "mail": "banana5593681@companydomain.com",
      "groop": "Unmanaged",
      "number": "+73176890053"
    },
    {
      "id": 52,
      "FullName": "Harry Glenn",
      "account": "companydomain/HarryGlenn",
      "mail": "axolotl9187629@companydomain.com",
      "groop": "CDN/Managers",
      "number": "+78298452103"
    },
    {
      "id": 53,
      "FullName": "Levi Jennings",
      "account": "companydomain/LeviJennings",
      "mail": "slim5063654@companydomain.com",
      "groop": "CDN/Top Kvants",
      "number": "+74012579385"
    },
    {
      "id": 54,
      "FullName": "Margaret Mares",
      "account": "companydomain/MargaretMares",
      "mail": "orthodox8805447@companydomain.com",
      "groop": "CDN/Top Kvants",
      "number": "+74690095197"
    },
    {
      "id": 55,
      "FullName": "William Lewis",
      "account": "companydomain/WilliamLewis",
      "mail": "pastoral3098253@companydomain.com",
      "groop": "CDN/CEO",
      "number": "+72755786221"
    },
    {
      "id": 56,
      "FullName": "Gladys Daniels",
      "account": "companydomain/GladysDaniels",
      "mail": "quixotic8745351@companydomain.com",
      "groop": "CDN/CEO",
      "number": "+73841484874"
    },
    {
      "id": 57,
      "FullName": "Maria Becker",
      "account": "companydomain/MariaBecker",
      "mail": "panther7726753@companydomain.com",
      "groop": "CDN/Top Kvants",
      "number": "+77901251616"
    },
    {
      "id": 58,
      "FullName": "Sharon Lasalle",
      "account": "companydomain/SharonLasalle",
      "mail": "quantum1454259@companydomain.com",
      "groop": "CDN/Human resources",
      "number": "+73579805004"
    },
    {
      "id": 59,
      "FullName": "Nathaniel Brown",
      "account": "companydomain/NathanielBrown",
      "mail": "fortunate9634493@companydomain.com",
      "groop": "CDN/Managers",
      "number": "+71647263003"
    },
    {
      "id": 60,
      "FullName": "Silvia Concepcion",
      "account": "companydomain/SilviaConcepcion",
      "mail": "awesome6126700@companydomain.com",
      "groop": "CDN/Top Kvants",
      "number": "+72781692551"
    },
    {
      "id": 61,
      "FullName": "Jonathan Calhoon",
      "account": "companydomain/JonathanCalhoon",
      "mail": "of6701374@companydomain.com",
      "groop": "CDN/Human resources",
      "number": "+72638120875"
    },
    {
      "id": 62,
      "FullName": "Frieda Mccully",
      "account": "companydomain/FriedaMccully",
      "mail": "axiomatic5245667@companydomain.com",
      "groop": "CDN/Top Kvants",
      "number": "+76191827615"
    },
    {
      "id": 63,
      "FullName": "Susan Manuel",
      "account": "companydomain/SusanManuel",
      "mail": "owl9580999@companydomain.com",
      "groop": "CDN/Financials",
      "number": "+76317230906"
    },
    {
      "id": 64,
      "FullName": "Donna Cisneros",
      "account": "companydomain/DonnaCisneros",
      "mail": "warranty7330461@companydomain.com",
      "groop": "CDN/Financials",
      "number": "+74784573204"
    },
    {
      "id": 65,
      "FullName": "Miriam Bateman",
      "account": "companydomain/MiriamBateman",
      "mail": "capable2648746@companydomain.com",
      "groop": "CDN/Managers",
      "number": "+76165964499"
    },
    {
      "id": 66,
      "FullName": "Kathleen Tierney",
      "account": "companydomain/KathleenTierney",
      "mail": "attack6607405@companydomain.com",
      "groop": "CDN/Sales",
      "number": "+73130340132"
    },
    {
      "id": 67,
      "FullName": "Cynthia Greene",
      "account": "companydomain/CynthiaGreene",
      "mail": "of5758416@companydomain.com",
      "groop": "Unmanaged",
      "number": "+74110030071"
    },
    {
      "id": 68,
      "FullName": "James Headrick",
      "account": "companydomain/JamesHeadrick",
      "mail": "sceptical8854884@companydomain.com",
      "groop": "CDN/Top Kvants",
      "number": "+76087659674"
    },
    {
      "id": 69,
      "FullName": "Cleo Tefft",
      "account": "companydomain/CleoTefft",
      "mail": "of2779574@companydomain.com",
      "groop": "CDN/Sales",
      "number": "+71543573259"
    },
    {
      "id": 70,
      "FullName": "James Harrison",
      "account": "companydomain/JamesHarrison",
      "mail": "parrot5880503@companydomain.com",
      "groop": "CDN/Managers",
      "number": "+71378517013"
    },
    {
      "id": 71,
      "FullName": "Diane Pugh",
      "account": "companydomain/DianePugh",
      "mail": "illustrious3805256@companydomain.com",
      "groop": "CDN/Managers",
      "number": "+73177461830"
    },
    {
      "id": 72,
      "FullName": "Jay Hernandez",
      "account": "companydomain/JayHernandez",
      "mail": "terrier1391974@companydomain.com",
      "groop": "CDN/Top Kvants",
      "number": "+77851470862"
    },
    {
      "id": 73,
      "FullName": "Judith Fergerson",
      "account": "companydomain/JudithFergerson",
      "mail": "penetration2177803@companydomain.com",
      "groop": "CDN/Sales",
      "number": "+71341057626"
    },
    {
      "id": 74,
      "FullName": "Angela Sims",
      "account": "companydomain/AngelaSims",
      "mail": "enlightened9424750@companydomain.com",
      "groop": "CDN/Top Kvants",
      "number": "+79441879219"
    },
    {
      "id": 75,
      "FullName": "Raul Reeves",
      "account": "companydomain/RaulReeves",
      "mail": "of3803230@companydomain.com",
      "groop": "CDN/Top Kvants",
      "number": "+75257916218"
    },
    {
      "id": 76,
      "FullName": "Steve Perry",
      "account": "companydomain/StevePerry",
      "mail": "glorious8692948@companydomain.com",
      "groop": "CDN/CEO",
      "number": "+71809210601"
    },
    {
      "id": 77,
      "FullName": "Corrine Gross",
      "account": "companydomain/CorrineGross",
      "mail": "leech1643071@companydomain.com",
      "groop": "CDN/Financials",
      "number": "+73620003267"
    },
    {
      "id": 78,
      "FullName": "Lizzie Kruse",
      "account": "companydomain/LizzieKruse",
      "mail": "llama8437045@companydomain.com",
      "groop": "Unmanaged",
      "number": "+71045071013"
    },
    {
      "id": 79,
      "FullName": "Joshua Ross",
      "account": "companydomain/JoshuaRoss",
      "mail": "dancing1877477@companydomain.com",
      "groop": "CDN/Human resources",
      "number": "+79041577129"
    },
    {
      "id": 80,
      "FullName": "Wilma Hodge",
      "account": "companydomain/WilmaHodge",
      "mail": "spotted3334450@companydomain.com",
      "groop": "CDN/Sales",
      "number": "+73548783174"
    },
    {
      "id": 81,
      "FullName": "Henry Meddaugh",
      "account": "companydomain/HenryMeddaugh",
      "mail": "eldorado9689258@companydomain.com",
      "groop": "CDN/Financials",
      "number": "+78211112099"
    },
    {
      "id": 82,
      "FullName": "Doris Rollins",
      "account": "companydomain/DorisRollins",
      "mail": "perspective6157093@companydomain.com",
      "groop": "CDN/CEO",
      "number": "+71866263938"
    },
    {
      "id": 83,
      "FullName": "Gloria Rose",
      "account": "companydomain/GloriaRose",
      "mail": "abiding6328270@companydomain.com",
      "groop": "CDN/Sales",
      "number": "+73824261944"
    },
    {
      "id": 84,
      "FullName": "Maureen Randall",
      "account": "companydomain/MaureenRandall",
      "mail": "butterfly1008901@companydomain.com",
      "groop": "Unmanaged",
      "number": "+77384602155"
    },
    {
      "id": 85,
      "FullName": "Reynaldo Page",
      "account": "companydomain/ReynaldoPage",
      "mail": "fanatic3145580@companydomain.com",
      "groop": "CDN/Sales",
      "number": "+77366218746"
    },
    {
      "id": 86,
      "FullName": "Jesse Farrell",
      "account": "companydomain/JesseFarrell",
      "mail": "free9193968@companydomain.com",
      "groop": "CDN/Managers",
      "number": "+79292728914"
    },
    {
      "id": 87,
      "FullName": "Francis Munoz",
      "account": "companydomain/FrancisMunoz",
      "mail": "defense1609748@companydomain.com",
      "groop": "Unmanaged",
      "number": "+74104086304"
    },
    {
      "id": 88,
      "FullName": "Tim King",
      "account": "companydomain/TimKing",
      "mail": "psychedelic8960808@companydomain.com",
      "groop": "CDN/CEO",
      "number": "+75981198960"
    },
    {
      "id": 89,
      "FullName": "June Jimmerson",
      "account": "companydomain/JuneJimmerson",
      "mail": "myna9322541@companydomain.com",
      "groop": "CDN/Top Kvants",
      "number": "+73708424569"
    },
    {
      "id": 90,
      "FullName": "Pamela Hill",
      "account": "companydomain/PamelaHill",
      "mail": "cautious1759230@companydomain.com",
      "groop": "Unmanaged",
      "number": "+78396627419"
    },
    {
      "id": 91,
      "FullName": "Frank Martin",
      "account": "companydomain/FrankMartin",
      "mail": "sparkling8239944@companydomain.com",
      "groop": "CDN/Sales",
      "number": "+77399103267"
    },
    {
      "id": 92,
      "FullName": "Raymond Taylor",
      "account": "companydomain/RaymondTaylor",
      "mail": "abstract5611838@companydomain.com",
      "groop": "CDN/Financials",
      "number": "+72841950514"
    },
    {
      "id": 93,
      "FullName": "Brigette Daniels",
      "account": "companydomain/BrigetteDaniels",
      "mail": "development6971672@companydomain.com",
      "groop": "CDN/Sales",
      "number": "+74956110853"
    },
    {
      "id": 94,
      "FullName": "Lois Gonzalez",
      "account": "companydomain/LoisGonzalez",
      "mail": "of5934889@companydomain.com",
      "groop": "CDN/Managers",
      "number": "+78176443507"
    },
    {
      "id": 95,
      "FullName": "Laura Frey",
      "account": "companydomain/LauraFrey",
      "mail": "futuristic2867712@companydomain.com",
      "groop": "Unmanaged",
      "number": "+72468142162"
    },
    {
      "id": 96,
      "FullName": "Juana Fruits",
      "account": "companydomain/JuanaFruits",
      "mail": "radiant1239459@companydomain.com",
      "groop": "CDN/Financials",
      "number": "+77143389537"
    },
    {
      "id": 97,
      "FullName": "Kara Rivard",
      "account": "companydomain/KaraRivard",
      "mail": "knowing1011607@companydomain.com",
      "groop": "CDN/Human resources",
      "number": "+78477051786"
    },
    {
      "id": 98,
      "FullName": "Michael Fleagle",
      "account": "companydomain/MichaelFleagle",
      "mail": "skinny8776851@companydomain.com",
      "groop": "CDN/Top Kvants",
      "number": "+79205279294"
    },
    {
      "id": 99,
      "FullName": "Donna Silva",
      "account": "companydomain/DonnaSilva",
      "mail": "speedy5333950@companydomain.com",
      "groop": "CDN/Human resources",
      "number": "+76438734259"
    },
    {
      "id": 100,
      "FullName": "Raymond Ortega",
      "account": "companydomain/RaymondOrtega",
      "mail": "dazzling583680@companydomain.com",
      "groop": "Unmanaged",
      "number": "+71340698019"
    },
    {
      "id": 101,
      "FullName": "Tonya Mccluskey",
      "account": "companydomain/TonyaMccluskey",
      "mail": "of3679916@companydomain.com",
      "groop": "CDN/Top Kvants",
      "number": "+72432933133"
    },
    {
      "id": 102,
      "FullName": "Janice Hunter",
      "account": "companydomain/JaniceHunter",
      "mail": "cuddly6203809@companydomain.com",
      "groop": "CDN/Top Kvants",
      "number": "+79553686485"
    },
    {
      "id": 103,
      "FullName": "Lois Johnson",
      "account": "companydomain/LoisJohnson",
      "mail": "brawny5462887@companydomain.com",
      "groop": "CDN/Financials",
      "number": "+72756386123"
    },
    {
      "id": 104,
      "FullName": "Molly Pitts",
      "account": "companydomain/MollyPitts",
      "mail": "visionary2456443@companydomain.com",
      "groop": "CDN/Sales",
      "number": "+73636275906"
    },
    {
      "id": 105,
      "FullName": "Joseph Zuidema",
      "account": "companydomain/JosephZuidema",
      "mail": "acceptance1579525@companydomain.com",
      "groop": "CDN/Sales",
      "number": "+73812825707"
    },
    {
      "id": 106,
      "FullName": "Annie Graves",
      "account": "companydomain/AnnieGraves",
      "mail": "benevolent2404458@companydomain.com",
      "groop": "CDN/Top Kvants",
      "number": "+77851704131"
    },
    {
      "id": 107,
      "FullName": "Jennifer Westbrook",
      "account": "companydomain/JenniferWestbrook",
      "mail": "green3956582@companydomain.com",
      "groop": "CDN/Financials",
      "number": "+73740017994"
    },
    {
      "id": 108,
      "FullName": "Marvin Walquist",
      "account": "companydomain/MarvinWalquist",
      "mail": "observant8299574@companydomain.com",
      "groop": "CDN/Financials",
      "number": "+71638781849"
    },
    {
      "id": 109,
      "FullName": "Nicolas Gouty",
      "account": "companydomain/NicolasGouty",
      "mail": "holistic7503039@companydomain.com",
      "groop": "CDN/Managers",
      "number": "+71304836969"
    },
    {
      "id": 110,
      "FullName": "Barry Paar",
      "account": "companydomain/BarryPaar",
      "mail": "ebony2321443@companydomain.com",
      "groop": "CDN/Human resources",
      "number": "+72570439543"
    },
    {
      "id": 111,
      "FullName": "James Odom",
      "account": "companydomain/JamesOdom",
      "mail": "poodle5303671@companydomain.com",
      "groop": "CDN/CEO",
      "number": "+73669684068"
    },
    {
      "id": 112,
      "FullName": "Ronnie Hawthorne",
      "account": "companydomain/RonnieHawthorne",
      "mail": "jackrabbit9363470@companydomain.com",
      "groop": "Unmanaged",
      "number": "+76149330597"
    },
    {
      "id": 113,
      "FullName": "Mitchell Nicholson",
      "account": "companydomain/MitchellNicholson",
      "mail": "neon77005@companydomain.com",
      "groop": "CDN/Managers",
      "number": "+76614748031"
    },
    {
      "id": 114,
      "FullName": "Brian Anderson",
      "account": "companydomain/BrianAnderson",
      "mail": "of4376504@companydomain.com",
      "groop": "CDN/Human resources",
      "number": "+77088172219"
    },
    {
      "id": 115,
      "FullName": "Alice Burris",
      "account": "companydomain/AliceBurris",
      "mail": "rational6458710@companydomain.com",
      "groop": "CDN/Managers",
      "number": "+74623608281"
    },
    {
      "id": 116,
      "FullName": "Donna Zigler",
      "account": "companydomain/DonnaZigler",
      "mail": "orange3799800@companydomain.com",
      "groop": "Unmanaged",
      "number": "+76002932435"
    },
    {
      "id": 117,
      "FullName": "Rachel Mcallister",
      "account": "companydomain/RachelMcallister",
      "mail": "mandrill2297988@companydomain.com",
      "groop": "Unmanaged",
      "number": "+76854894113"
    },
    {
      "id": 118,
      "FullName": "Robert Smith",
      "account": "companydomain/RobertSmith",
      "mail": "octopus7528230@companydomain.com",
      "groop": "CDN/Managers",
      "number": "+79648994414"
    },
    {
      "id": 119,
      "FullName": "Tommy Campbell",
      "account": "companydomain/TommyCampbell",
      "mail": "flawless852186@companydomain.com",
      "groop": "Unmanaged",
      "number": "+78335902553"
    },
    {
      "id": 120,
      "FullName": "Jolene Kelly",
      "account": "companydomain/JoleneKelly",
      "mail": "terrier6964928@companydomain.com",
      "groop": "CDN/Human resources",
      "number": "+76291935334"
    },
    {
      "id": 121,
      "FullName": "Charles Smith",
      "account": "companydomain/CharlesSmith",
      "mail": "of8581196@companydomain.com",
      "groop": "CDN/Sales",
      "number": "+79391225875"
    },
    {
      "id": 122,
      "FullName": "Brandon Vazquez",
      "account": "companydomain/BrandonVazquez",
      "mail": "golden4468465@companydomain.com",
      "groop": "CDN/Sales",
      "number": "+77531095422"
    },
    {
      "id": 123,
      "FullName": "William Triplett",
      "account": "companydomain/WilliamTriplett",
      "mail": "trout8151762@companydomain.com",
      "groop": "Unmanaged",
      "number": "+73591474108"
    },
    {
      "id": 124,
      "FullName": "Mary Harris",
      "account": "companydomain/MaryHarris",
      "mail": "devout4372138@companydomain.com",
      "groop": "CDN/Sales",
      "number": "+72184060583"
    },
    {
      "id": 125,
      "FullName": "Russell Neff",
      "account": "companydomain/RussellNeff",
      "mail": "perception5870945@companydomain.com",
      "groop": "CDN/CEO",
      "number": "+75063140678"
    },
    {
      "id": 126,
      "FullName": "Theresa Tong",
      "account": "companydomain/TheresaTong",
      "mail": "of4110452@companydomain.com",
      "groop": "CDN/Sales",
      "number": "+76889895183"
    },
    {
      "id": 127,
      "FullName": "Elizabeth Bowers",
      "account": "companydomain/ElizabethBowers",
      "mail": "of208086@companydomain.com",
      "groop": "CDN/Human resources",
      "number": "+76697611002"
    },
    {
      "id": 128,
      "FullName": "Linda Dunn",
      "account": "companydomain/LindaDunn",
      "mail": "of6111881@companydomain.com",
      "groop": "CDN/Managers",
      "number": "+71432578897"
    },
    {
      "id": 129,
      "FullName": "Scott Wickham",
      "account": "companydomain/ScottWickham",
      "mail": "benevolent271932@companydomain.com",
      "groop": "CDN/Top Kvants",
      "number": "+76995348131"
    },
    {
      "id": 130,
      "FullName": "Herbert Kendrick",
      "account": "companydomain/HerbertKendrick",
      "mail": "hyperborea5857727@companydomain.com",
      "groop": "CDN/CEO",
      "number": "+77979007488"
    },
    {
      "id": 131,
      "FullName": "Otis Olguin",
      "account": "companydomain/OtisOlguin",
      "mail": "of371458@companydomain.com",
      "groop": "CDN/CEO",
      "number": "+72903382438"
    },
    {
      "id": 132,
      "FullName": "Nancy Tucker",
      "account": "companydomain/NancyTucker",
      "mail": "degu9802512@companydomain.com",
      "groop": "CDN/CEO",
      "number": "+75068462275"
    },
    {
      "id": 133,
      "FullName": "Leah Quackenbush",
      "account": "companydomain/LeahQuackenbush",
      "mail": "quail1652101@companydomain.com",
      "groop": "CDN/Human resources",
      "number": "+75810274760"
    },
    {
      "id": 134,
      "FullName": "Michael Martinez",
      "account": "companydomain/MichaelMartinez",
      "mail": "realistic5737295@companydomain.com",
      "groop": "CDN/Sales",
      "number": "+77653403430"
    },
    {
      "id": 135,
      "FullName": "Joey Cantrell",
      "account": "companydomain/JoeyCantrell",
      "mail": "colossal153623@companydomain.com",
      "groop": "CDN/Top Kvants",
      "number": "+75980578922"
    },
    {
      "id": 136,
      "FullName": "Barbara Cottingham",
      "account": "companydomain/BarbaraCottingham",
      "mail": "enchanted2133810@companydomain.com",
      "groop": "CDN/Financials",
      "number": "+76548382652"
    },
    {
      "id": 137,
      "FullName": "Lisa Keim",
      "account": "companydomain/LisaKeim",
      "mail": "uptight6108271@companydomain.com",
      "groop": "CDN/Managers",
      "number": "+78534376243"
    },
    {
      "id": 138,
      "FullName": "Brandy Mcclure",
      "account": "companydomain/BrandyMcclure",
      "mail": "security1178416@companydomain.com",
      "groop": "CDN/Financials",
      "number": "+73506378640"
    },
    {
      "id": 139,
      "FullName": "Lurline Echevarria",
      "account": "companydomain/LurlineEchevarria",
      "mail": "blond1590395@companydomain.com",
      "groop": "CDN/Sales",
      "number": "+73568766262"
    },
    {
      "id": 140,
      "FullName": "Jeanette Roberts",
      "account": "companydomain/JeanetteRoberts",
      "mail": "mysterious894921@companydomain.com",
      "groop": "CDN/Human resources",
      "number": "+74795531342"
    },
    {
      "id": 141,
      "FullName": "Paul Stahl",
      "account": "companydomain/PaulStahl",
      "mail": "beetle631588@companydomain.com",
      "groop": "CDN/Human resources",
      "number": "+72295428165"
    },
    {
      "id": 142,
      "FullName": "Terry Lenz",
      "account": "companydomain/TerryLenz",
      "mail": "miniature8971452@companydomain.com",
      "groop": "Unmanaged",
      "number": "+71114708473"
    },
    {
      "id": 143,
      "FullName": "Lauren Chapman",
      "account": "companydomain/LaurenChapman",
      "mail": "omniscient1244427@companydomain.com",
      "groop": "CDN/Sales",
      "number": "+74714674012"
    },
    {
      "id": 144,
      "FullName": "Gladys Mcswain",
      "account": "companydomain/GladysMcswain",
      "mail": "mini8026981@companydomain.com",
      "groop": "CDN/Sales",
      "number": "+72922812473"
    },
    {
      "id": 145,
      "FullName": "Larry Falgoust",
      "account": "companydomain/LarryFalgoust",
      "mail": "rough43211@companydomain.com",
      "groop": "CDN/Top Kvants",
      "number": "+76010190731"
    },
    {
      "id": 146,
      "FullName": "Brian Howard",
      "account": "companydomain/BrianHoward",
      "mail": "of108464@companydomain.com",
      "groop": "Unmanaged",
      "number": "+72479451310"
    },
    {
      "id": 147,
      "FullName": "Catherine Mirr",
      "account": "companydomain/CatherineMirr",
      "mail": "from9892763@companydomain.com",
      "groop": "CDN/Financials",
      "number": "+79294867718"
    },
    {
      "id": 148,
      "FullName": "Rick Duckett",
      "account": "companydomain/RickDuckett",
      "mail": "exercise9532736@companydomain.com",
      "groop": "CDN/Human resources",
      "number": "+75958012429"
    },
    {
      "id": 149,
      "FullName": "Pamela Fairhurst",
      "account": "companydomain/PamelaFairhurst",
      "mail": "vigilant1629655@companydomain.com",
      "groop": "CDN/Sales",
      "number": "+73328447055"
    },
    {
      "id": 150,
      "FullName": "Mark Edemann",
      "account": "companydomain/MarkEdemann",
      "mail": "of4790570@companydomain.com",
      "groop": "Unmanaged",
      "number": "+71273479505"
    },
    {
      "id": 151,
      "FullName": "Edward Harter",
      "account": "companydomain/EdwardHarter",
      "mail": "curly8533959@companydomain.com",
      "groop": "CDN/Human resources",
      "number": "+72961656906"
    },
    {
      "id": 152,
      "FullName": "Sean Entrekin",
      "account": "companydomain/SeanEntrekin",
      "mail": "nuthatch3252091@companydomain.com",
      "groop": "CDN/Top Kvants",
      "number": "+73638316611"
    },
    {
      "id": 153,
      "FullName": "Anna Lacy",
      "account": "companydomain/AnnaLacy",
      "mail": "aptitude6523435@companydomain.com",
      "groop": "CDN/Sales",
      "number": "+71789514259"
    },
    {
      "id": 154,
      "FullName": "Dorothy Kirk",
      "account": "companydomain/DorothyKirk",
      "mail": "opalescent7091427@companydomain.com",
      "groop": "CDN/Human resources",
      "number": "+71746881671"
    },
    {
      "id": 155,
      "FullName": "Marisol Willert",
      "account": "companydomain/MarisolWillert",
      "mail": "mink9313666@companydomain.com",
      "groop": "CDN/Managers",
      "number": "+74594474799"
    },
    {
      "id": 156,
      "FullName": "Juan Shreve",
      "account": "companydomain/JuanShreve",
      "mail": "gaiety6868213@companydomain.com",
      "groop": "CDN/Sales",
      "number": "+79631019689"
    },
    {
      "id": 157,
      "FullName": "Brenna Cope",
      "account": "companydomain/BrennaCope",
      "mail": "climate2112012@companydomain.com",
      "groop": "CDN/Top Kvants",
      "number": "+77525846990"
    },
    {
      "id": 158,
      "FullName": "Bert Roddick",
      "account": "companydomain/BertRoddick",
      "mail": "mole8080910@companydomain.com",
      "groop": "CDN/Managers",
      "number": "+75318917648"
    },
    {
      "id": 159,
      "FullName": "Doreen Vogel",
      "account": "companydomain/DoreenVogel",
      "mail": "pleasure4964584@companydomain.com",
      "groop": "CDN/Human resources",
      "number": "+74988647945"
    },
    {
      "id": 160,
      "FullName": "Kathleen Lawson",
      "account": "companydomain/KathleenLawson",
      "mail": "leadership7108765@companydomain.com",
      "groop": "CDN/Human resources",
      "number": "+72209058594"
    },
    {
      "id": 161,
      "FullName": "Jennifer Sneed",
      "account": "companydomain/JenniferSneed",
      "mail": "diversity3672984@companydomain.com",
      "groop": "CDN/Sales",
      "number": "+74550292170"
    },
    {
      "id": 162,
      "FullName": "Michelle Davis",
      "account": "companydomain/MichelleDavis",
      "mail": "goose424611@companydomain.com",
      "groop": "Unmanaged",
      "number": "+78910670716"
    },
    {
      "id": 163,
      "FullName": "Thomas Cleveland",
      "account": "companydomain/ThomasCleveland",
      "mail": "warranty1246812@companydomain.com",
      "groop": "CDN/Human resources",
      "number": "+74978703466"
    },
    {
      "id": 164,
      "FullName": "Anna Mcwhirter",
      "account": "companydomain/AnnaMcwhirter",
      "mail": "dragonfly2710221@companydomain.com",
      "groop": "CDN/Top Kvants",
      "number": "+77833437220"
    },
    {
      "id": 165,
      "FullName": "Robert Jones",
      "account": "companydomain/RobertJones",
      "mail": "pleasure9660364@companydomain.com",
      "groop": "Unmanaged",
      "number": "+78546507475"
    },
    {
      "id": 166,
      "FullName": "Elma Navarro",
      "account": "companydomain/ElmaNavarro",
      "mail": "dragonfly8784980@companydomain.com",
      "groop": "CDN/Sales",
      "number": "+71988541995"
    },
    {
      "id": 167,
      "FullName": "Tammy Snow",
      "account": "companydomain/TammySnow",
      "mail": "spider2597816@companydomain.com",
      "groop": "CDN/CEO",
      "number": "+75315596283"
    },
    {
      "id": 168,
      "FullName": "James Jordan",
      "account": "companydomain/JamesJordan",
      "mail": "wildebeest1484304@companydomain.com",
      "groop": "Unmanaged",
      "number": "+74266036741"
    },
    {
      "id": 169,
      "FullName": "Frank Wells",
      "account": "companydomain/FrankWells",
      "mail": "admiration4446327@companydomain.com",
      "groop": "CDN/Sales",
      "number": "+75893584019"
    },
    {
      "id": 170,
      "FullName": "Fletcher Joyce",
      "account": "companydomain/FletcherJoyce",
      "mail": "junglefowl4679617@companydomain.com",
      "groop": "CDN/Human resources",
      "number": "+77755253891"
    },
    {
      "id": 171,
      "FullName": "Shirley Reese",
      "account": "companydomain/ShirleyReese",
      "mail": "from9749399@companydomain.com",
      "groop": "CDN/Human resources",
      "number": "+79358935858"
    },
    {
      "id": 172,
      "FullName": "Josephina Matuszewski",
      "account": "companydomain/JosephinaMatuszewski",
      "mail": "basilisk4910215@companydomain.com",
      "groop": "CDN/Sales",
      "number": "+79886038645"
    },
    {
      "id": 173,
      "FullName": "Robert Chiesa",
      "account": "companydomain/RobertChiesa",
      "mail": "energy905678@companydomain.com",
      "groop": "Unmanaged",
      "number": "+79442554855"
    },
    {
      "id": 174,
      "FullName": "Joseph Powell",
      "account": "companydomain/JosephPowell",
      "mail": "current2712991@companydomain.com",
      "groop": "CDN/Managers",
      "number": "+77140328410"
    },
    {
      "id": 175,
      "FullName": "Paula Gilbert",
      "account": "companydomain/PaulaGilbert",
      "mail": "sturdy4228856@companydomain.com",
      "groop": "CDN/Managers",
      "number": "+72312535764"
    },
    {
      "id": 176,
      "FullName": "Luis Berry",
      "account": "companydomain/LuisBerry",
      "mail": "mole3223562@companydomain.com",
      "groop": "CDN/Top Kvants",
      "number": "+79003342073"
    },
    {
      "id": 177,
      "FullName": "Brittany Woodall",
      "account": "companydomain/BrittanyWoodall",
      "mail": "flawless2944592@companydomain.com",
      "groop": "CDN/Human resources",
      "number": "+73758908547"
    },
    {
      "id": 178,
      "FullName": "Brian Fox",
      "account": "companydomain/BrianFox",
      "mail": "mackerel1172682@companydomain.com",
      "groop": "CDN/CEO",
      "number": "+73070259778"
    },
    {
      "id": 179,
      "FullName": "Darin Windly",
      "account": "companydomain/DarinWindly",
      "mail": "pluto9835265@companydomain.com",
      "groop": "CDN/Financials",
      "number": "+78391916303"
    },
    {
      "id": 180,
      "FullName": "Josephine Strauch",
      "account": "companydomain/JosephineStrauch",
      "mail": "spiritual2852982@companydomain.com",
      "groop": "Unmanaged",
      "number": "+73636228153"
    },
    {
      "id": 181,
      "FullName": "Sharon Rogers",
      "account": "companydomain/SharonRogers",
      "mail": "agreement2602030@companydomain.com",
      "groop": "Unmanaged",
      "number": "+79936507642"
    },
    {
      "id": 182,
      "FullName": "Sandra James",
      "account": "companydomain/SandraJames",
      "mail": "arboreal1877151@companydomain.com",
      "groop": "CDN/Sales",
      "number": "+79201490575"
    },
    {
      "id": 183,
      "FullName": "Dante Sailors",
      "account": "companydomain/DanteSailors",
      "mail": "excellent5005404@companydomain.com",
      "groop": "CDN/Sales",
      "number": "+79159119559"
    },
    {
      "id": 184,
      "FullName": "Michelle Kozma",
      "account": "companydomain/MichelleKozma",
      "mail": "prestige7640296@companydomain.com",
      "groop": "CDN/Top Kvants",
      "number": "+74489772619"
    },
    {
      "id": 185,
      "FullName": "Juanita Ricketts",
      "account": "companydomain/JuanitaRicketts",
      "mail": "chihuahua27777@companydomain.com",
      "groop": "CDN/Top Kvants",
      "number": "+76153532054"
    },
    {
      "id": 186,
      "FullName": "Gabriel Myers",
      "account": "companydomain/GabrielMyers",
      "mail": "admiration1936325@companydomain.com",
      "groop": "CDN/Sales",
      "number": "+77064539469"
    },
    {
      "id": 187,
      "FullName": "Susan Evans",
      "account": "companydomain/SusanEvans",
      "mail": "meteoric1717847@companydomain.com",
      "groop": "CDN/Managers",
      "number": "+73149989883"
    },
    {
      "id": 188,
      "FullName": "Alice Boldt",
      "account": "companydomain/AliceBoldt",
      "mail": "eminent3438603@companydomain.com",
      "groop": "CDN/Top Kvants",
      "number": "+77998712317"
    },
    {
      "id": 189,
      "FullName": "Ernest Alvez",
      "account": "companydomain/ErnestAlvez",
      "mail": "astute2672053@companydomain.com",
      "groop": "CDN/Managers",
      "number": "+72667692162"
    },
    {
      "id": 190,
      "FullName": "Richard Meader",
      "account": "companydomain/RichardMeader",
      "mail": "of7978330@companydomain.com",
      "groop": "CDN/Top Kvants",
      "number": "+78596596065"
    },
    {
      "id": 191,
      "FullName": "Peter Lieberman",
      "account": "companydomain/PeterLieberman",
      "mail": "exotic5733484@companydomain.com",
      "groop": "CDN/Sales",
      "number": "+77909314982"
    },
    {
      "id": 192,
      "FullName": "Craig Tamaro",
      "account": "companydomain/CraigTamaro",
      "mail": "bonobo46736@companydomain.com",
      "groop": "CDN/Human resources",
      "number": "+78695475836"
    },
    {
      "id": 193,
      "FullName": "Celeste Defreitas",
      "account": "companydomain/CelesteDefreitas",
      "mail": "certainty2042784@companydomain.com",
      "groop": "CDN/Managers",
      "number": "+78381182270"
    },
    {
      "id": 194,
      "FullName": "Gregory Smith",
      "account": "companydomain/GregorySmith",
      "mail": "of1724173@companydomain.com",
      "groop": "Unmanaged",
      "number": "+74250525136"
    },
    {
      "id": 195,
      "FullName": "Erika Asato",
      "account": "companydomain/ErikaAsato",
      "mail": "tough2840392@companydomain.com",
      "groop": "Unmanaged",
      "number": "+71694290529"
    },
    {
      "id": 196,
      "FullName": "John Kinchen",
      "account": "companydomain/JohnKinchen",
      "mail": "cornflower1955383@companydomain.com",
      "groop": "CDN/Managers",
      "number": "+72399278871"
    },
    {
      "id": 197,
      "FullName": "Michael Parker",
      "account": "companydomain/MichaelParker",
      "mail": "proud7569098@companydomain.com",
      "groop": "CDN/Managers",
      "number": "+74478479807"
    },
    {
      "id": 198,
      "FullName": "Esther Gipson",
      "account": "companydomain/EstherGipson",
      "mail": "prompt5863743@companydomain.com",
      "groop": "CDN/Top Kvants",
      "number": "+75312712040"
    },
    {
      "id": 199,
      "FullName": "Barbara Mclarney",
      "account": "companydomain/BarbaraMclarney",
      "mail": "tranquility4448017@companydomain.com",
      "groop": "Unmanaged",
      "number": "+77610288788"
    },
    {
      "id": 200,
      "FullName": "Anna Thornton",
      "account": "companydomain/AnnaThornton",
      "mail": "uber3799359@companydomain.com",
      "groop": "CDN/Top Kvants",
      "number": "+74383710625"
    },
    {
      "id": 201,
      "FullName": "Edwin Ditullio",
      "account": "companydomain/EdwinDitullio",
      "mail": "passion7518557@companydomain.com",
      "groop": "CDN/Managers",
      "number": "+77220177716"
    },
    {
      "id": 202,
      "FullName": "Robert Rivas",
      "account": "companydomain/RobertRivas",
      "mail": "criticism2294452@companydomain.com",
      "groop": "CDN/CEO",
      "number": "+79486946434"
    },
    {
      "id": 203,
      "FullName": "Danielle Lafond",
      "account": "companydomain/DanielleLafond",
      "mail": "patience8778928@companydomain.com",
      "groop": "CDN/CEO",
      "number": "+74743734345"
    },
    {
      "id": 204,
      "FullName": "Deanna Templeton",
      "account": "companydomain/DeannaTempleton",
      "mail": "stimulating713248@companydomain.com",
      "groop": "CDN/Top Kvants",
      "number": "+74486590587"
    },
    {
      "id": 205,
      "FullName": "Terry Main",
      "account": "companydomain/TerryMain",
      "mail": "mars8275028@companydomain.com",
      "groop": "CDN/Managers",
      "number": "+73898356593"
    },
    {
      "id": 206,
      "FullName": "Cecila Taylor",
      "account": "companydomain/CecilaTaylor",
      "mail": "of2762552@companydomain.com",
      "groop": "CDN/Managers",
      "number": "+76575986852"
    },
    {
      "id": 207,
      "FullName": "James Davidson",
      "account": "companydomain/JamesDavidson",
      "mail": "opal5496526@companydomain.com",
      "groop": "CDN/Financials",
      "number": "+77650985020"
    },
    {
      "id": 208,
      "FullName": "Margaret Jensen",
      "account": "companydomain/MargaretJensen",
      "mail": "expert7762381@companydomain.com",
      "groop": "CDN/Human resources",
      "number": "+73686078050"
    },
    {
      "id": 209,
      "FullName": "Betty Mancine",
      "account": "companydomain/BettyMancine",
      "mail": "archetypal5328653@companydomain.com",
      "groop": "CDN/Top Kvants",
      "number": "+75014691259"
    },
    {
      "id": 210,
      "FullName": "Starla Christin",
      "account": "companydomain/StarlaChristin",
      "mail": "llama8746272@companydomain.com",
      "groop": "CDN/CEO",
      "number": "+77694238432"
    },
    {
      "id": 211,
      "FullName": "James Polk",
      "account": "companydomain/JamesPolk",
      "mail": "amiable8051098@companydomain.com",
      "groop": "CDN/Top Kvants",
      "number": "+79463988226"
    },
    {
      "id": 212,
      "FullName": "Mildred Wampler",
      "account": "companydomain/MildredWampler",
      "mail": "management7029757@companydomain.com",
      "groop": "CDN/Managers",
      "number": "+72716221852"
    },
    {
      "id": 213,
      "FullName": "Christopher Hunnings",
      "account": "companydomain/ChristopherHunnings",
      "mail": "painting5842199@companydomain.com",
      "groop": "CDN/Sales",
      "number": "+79768039176"
    },
    {
      "id": 214,
      "FullName": "William Archambeault",
      "account": "companydomain/WilliamArchambeault",
      "mail": "heavenly1283788@companydomain.com",
      "groop": "CDN/CEO",
      "number": "+74845912335"
    },
    {
      "id": 215,
      "FullName": "Kathryn Braddy",
      "account": "companydomain/KathrynBraddy",
      "mail": "persistence4902679@companydomain.com",
      "groop": "CDN/CEO",
      "number": "+71487175477"
    },
    {
      "id": 216,
      "FullName": "Rosetta Davis",
      "account": "companydomain/RosettaDavis",
      "mail": "management1602867@companydomain.com",
      "groop": "CDN/Financials",
      "number": "+79089753656"
    },
    {
      "id": 217,
      "FullName": "Billy Carroll",
      "account": "companydomain/BillyCarroll",
      "mail": "noisy8523253@companydomain.com",
      "groop": "CDN/Top Kvants",
      "number": "+79811140117"
    },
    {
      "id": 218,
      "FullName": "Chester Davis",
      "account": "companydomain/ChesterDavis",
      "mail": "of378669@companydomain.com",
      "groop": "CDN/Financials",
      "number": "+79764437652"
    },
    {
      "id": 219,
      "FullName": "Stanley Pickering",
      "account": "companydomain/StanleyPickering",
      "mail": "hissing123040@companydomain.com",
      "groop": "Unmanaged",
      "number": "+73369967052"
    },
    {
      "id": 220,
      "FullName": "Peggy Lane",
      "account": "companydomain/PeggyLane",
      "mail": "demonic766390@companydomain.com",
      "groop": "Unmanaged",
      "number": "+73889443525"
    },
    {
      "id": 221,
      "FullName": "Cythia Mccardle",
      "account": "companydomain/CythiaMccardle",
      "mail": "of2789935@companydomain.com",
      "groop": "CDN/Human resources",
      "number": "+71725426895"
    },
    {
      "id": 222,
      "FullName": "Jennifer Gallardo",
      "account": "companydomain/JenniferGallardo",
      "mail": "premium7857486@companydomain.com",
      "groop": "CDN/Financials",
      "number": "+74731057457"
    },
    {
      "id": 223,
      "FullName": "Kenneth Stelk",
      "account": "companydomain/KennethStelk",
      "mail": "of5753551@companydomain.com",
      "groop": "Unmanaged",
      "number": "+73328347307"
    },
    {
      "id": 224,
      "FullName": "Gregg Bunnell",
      "account": "companydomain/GreggBunnell",
      "mail": "of3353375@companydomain.com",
      "groop": "CDN/Managers",
      "number": "+79414581336"
    },
    {
      "id": 225,
      "FullName": "Ginger Turner",
      "account": "companydomain/GingerTurner",
      "mail": "impetuous3458852@companydomain.com",
      "groop": "Unmanaged",
      "number": "+71363517519"
    },
    {
      "id": 226,
      "FullName": "William Olenick",
      "account": "companydomain/WilliamOlenick",
      "mail": "peace2094215@companydomain.com",
      "groop": "CDN/Human resources",
      "number": "+75654766516"
    },
    {
      "id": 227,
      "FullName": "Lisa Neyman",
      "account": "companydomain/LisaNeyman",
      "mail": "advertising8306413@companydomain.com",
      "groop": "CDN/Financials",
      "number": "+76929681563"
    },
    {
      "id": 228,
      "FullName": "Doris Parker",
      "account": "companydomain/DorisParker",
      "mail": "fennec3169019@companydomain.com",
      "groop": "CDN/Financials",
      "number": "+75384365339"
    },
    {
      "id": 229,
      "FullName": "Ray Lee",
      "account": "companydomain/RayLee",
      "mail": "garrulous8976229@companydomain.com",
      "groop": "CDN/Managers",
      "number": "+73235155099"
    },
    {
      "id": 230,
      "FullName": "Robert Beaver",
      "account": "companydomain/RobertBeaver",
      "mail": "of3892759@companydomain.com",
      "groop": "CDN/Financials",
      "number": "+72276012046"
    },
    {
      "id": 231,
      "FullName": "Terry Hawk",
      "account": "companydomain/TerryHawk",
      "mail": "asgard5646944@companydomain.com",
      "groop": "CDN/Top Kvants",
      "number": "+79599551226"
    },
    {
      "id": 232,
      "FullName": "Melissa Williams",
      "account": "companydomain/MelissaWilliams",
      "mail": "fancy307085@companydomain.com",
      "groop": "CDN/CEO",
      "number": "+78329791594"
    },
    {
      "id": 233,
      "FullName": "Jennifer Chafin",
      "account": "companydomain/JenniferChafin",
      "mail": "white2438392@companydomain.com",
      "groop": "CDN/Human resources",
      "number": "+72874421240"
    },
    {
      "id": 234,
      "FullName": "Robt Mcfadden",
      "account": "companydomain/RobtMcfadden",
      "mail": "popularity9385508@companydomain.com",
      "groop": "CDN/Human resources",
      "number": "+78615726295"
    },
    {
      "id": 235,
      "FullName": "Alfred Tapp",
      "account": "companydomain/AlfredTapp",
      "mail": "shrewd4225446@companydomain.com",
      "groop": "CDN/Financials",
      "number": "+77245797974"
    },
    {
      "id": 236,
      "FullName": "Stacy Peterson",
      "account": "companydomain/StacyPeterson",
      "mail": "total370981@companydomain.com",
      "groop": "CDN/CEO",
      "number": "+78315189783"
    },
    {
      "id": 237,
      "FullName": "Wilma Weaver",
      "account": "companydomain/WilmaWeaver",
      "mail": "skunk9515409@companydomain.com",
      "groop": "CDN/Financials",
      "number": "+73071341167"
    },
    {
      "id": 238,
      "FullName": "Dennis Gallaway",
      "account": "companydomain/DennisGallaway",
      "mail": "visionary237195@companydomain.com",
      "groop": "CDN/Sales",
      "number": "+73758758907"
    },
    {
      "id": 239,
      "FullName": "Mario Henson",
      "account": "companydomain/MarioHenson",
      "mail": "perception5359343@companydomain.com",
      "groop": "CDN/Top Kvants",
      "number": "+71514155700"
    },
    {
      "id": 240,
      "FullName": "Renee Mayfield",
      "account": "companydomain/ReneeMayfield",
      "mail": "crystal4724900@companydomain.com",
      "groop": "CDN/Managers",
      "number": "+72810772462"
    },
    {
      "id": 241,
      "FullName": "Elin Livingston",
      "account": "companydomain/ElinLivingston",
      "mail": "of9217374@companydomain.com",
      "groop": "Unmanaged",
      "number": "+71176976077"
    },
    {
      "id": 242,
      "FullName": "John Erwin",
      "account": "companydomain/JohnErwin",
      "mail": "mole8507550@companydomain.com",
      "groop": "CDN/Sales",
      "number": "+72349499477"
    },
    {
      "id": 243,
      "FullName": "Madeline Smith",
      "account": "companydomain/MadelineSmith",
      "mail": "tartarus3329832@companydomain.com",
      "groop": "CDN/Managers",
      "number": "+74431922959"
    },
    {
      "id": 244,
      "FullName": "Lee Boeke",
      "account": "companydomain/LeeBoeke",
      "mail": "bear3227274@companydomain.com",
      "groop": "Unmanaged",
      "number": "+72367740851"
    },
    {
      "id": 245,
      "FullName": "Ronald Sample",
      "account": "companydomain/RonaldSample",
      "mail": "of885960@companydomain.com",
      "groop": "CDN/Human resources",
      "number": "+79271252861"
    },
    {
      "id": 246,
      "FullName": "Libby Reasoner",
      "account": "companydomain/LibbyReasoner",
      "mail": "loon8071524@companydomain.com",
      "groop": "CDN/CEO",
      "number": "+75599010197"
    },
    {
      "id": 247,
      "FullName": "Karen Jones",
      "account": "companydomain/KarenJones",
      "mail": "of1342982@companydomain.com",
      "groop": "CDN/Managers",
      "number": "+76102069954"
    },
    {
      "id": 248,
      "FullName": "Marie Stanley",
      "account": "companydomain/MarieStanley",
      "mail": "novelty3761452@companydomain.com",
      "groop": "CDN/Sales",
      "number": "+72819581729"
    },
    {
      "id": 249,
      "FullName": "Robert Barnett",
      "account": "companydomain/RobertBarnett",
      "mail": "of272409@companydomain.com",
      "groop": "CDN/CEO",
      "number": "+71925053474"
    },
    {
      "id": 250,
      "FullName": "Ann Shams",
      "account": "companydomain/AnnShams",
      "mail": "dalmatian1276875@companydomain.com",
      "groop": "CDN/Human resources",
      "number": "+71315212139"
    },
    {
      "id": 251,
      "FullName": "Arthur Mason",
      "account": "companydomain/ArthurMason",
      "mail": "from5719177@companydomain.com",
      "groop": "Unmanaged",
      "number": "+79012537367"
    },
    {
      "id": 252,
      "FullName": "Bobbie Safford",
      "account": "companydomain/BobbieSafford",
      "mail": "skill1336448@companydomain.com",
      "groop": "CDN/Managers",
      "number": "+75888986207"
    },
    {
      "id": 253,
      "FullName": "Emilio Pena",
      "account": "companydomain/EmilioPena",
      "mail": "turkey9926849@companydomain.com",
      "groop": "CDN/Top Kvants",
      "number": "+74509951468"
    },
    {
      "id": 254,
      "FullName": "Caroline Cordoba",
      "account": "companydomain/CarolineCordoba",
      "mail": "naughty320033@companydomain.com",
      "groop": "CDN/Sales",
      "number": "+79914009018"
    },
    {
      "id": 255,
      "FullName": "Anita Pimentel",
      "account": "companydomain/AnitaPimentel",
      "mail": "psychedelic7057796@companydomain.com",
      "groop": "CDN/Top Kvants",
      "number": "+74737924997"
    },
    {
      "id": 256,
      "FullName": "Trina Nunmaker",
      "account": "companydomain/TrinaNunmaker",
      "mail": "marmot9207391@companydomain.com",
      "groop": "Unmanaged",
      "number": "+79564082491"
    },
    {
      "id": 257,
      "FullName": "Raymond Duck",
      "account": "companydomain/RaymondDuck",
      "mail": "dancing4641358@companydomain.com",
      "groop": "CDN/CEO",
      "number": "+78352770722"
    },
    {
      "id": 258,
      "FullName": "Brooke Gilmartin",
      "account": "companydomain/BrookeGilmartin",
      "mail": "secret3634742@companydomain.com",
      "groop": "Unmanaged",
      "number": "+71788657063"
    },
    {
      "id": 259,
      "FullName": "Angela Durham",
      "account": "companydomain/AngelaDurham",
      "mail": "cat8273819@companydomain.com",
      "groop": "Unmanaged",
      "number": "+72142167894"
    },
    {
      "id": 260,
      "FullName": "Eddie Barbee",
      "account": "companydomain/EddieBarbee",
      "mail": "of3922147@companydomain.com",
      "groop": "CDN/Managers",
      "number": "+75967260416"
    },
    {
      "id": 261,
      "FullName": "Marcia Vargas",
      "account": "companydomain/MarciaVargas",
      "mail": "of5597463@companydomain.com",
      "groop": "Unmanaged",
      "number": "+79199489923"
    },
    {
      "id": 262,
      "FullName": "George Shore",
      "account": "companydomain/GeorgeShore",
      "mail": "sawfly4988583@companydomain.com",
      "groop": "CDN/Top Kvants",
      "number": "+74995928912"
    },
    {
      "id": 263,
      "FullName": "Steve Bucy",
      "account": "companydomain/SteveBucy",
      "mail": "malkoha1276173@companydomain.com",
      "groop": "CDN/Human resources",
      "number": "+79496595456"
    },
    {
      "id": 264,
      "FullName": "Carlos Gage",
      "account": "companydomain/CarlosGage",
      "mail": "illegal3247540@companydomain.com",
      "groop": "CDN/Human resources",
      "number": "+75895757810"
    },
    {
      "id": 265,
      "FullName": "David Thornton",
      "account": "companydomain/DavidThornton",
      "mail": "mussel9192641@companydomain.com",
      "groop": "CDN/Human resources",
      "number": "+78307068826"
    },
    {
      "id": 266,
      "FullName": "Robert Brereton",
      "account": "companydomain/RobertBrereton",
      "mail": "fuzzy3322927@companydomain.com",
      "groop": "CDN/Top Kvants",
      "number": "+73752206267"
    },
    {
      "id": 267,
      "FullName": "James Dixon",
      "account": "companydomain/JamesDixon",
      "mail": "vivacious3130882@companydomain.com",
      "groop": "CDN/Financials",
      "number": "+72998818177"
    },
    {
      "id": 268,
      "FullName": "Irene Walter",
      "account": "companydomain/IreneWalter",
      "mail": "of7219109@companydomain.com",
      "groop": "CDN/Managers",
      "number": "+74769818137"
    },
    {
      "id": 269,
      "FullName": "Kenneth Neuhoff",
      "account": "companydomain/KennethNeuhoff",
      "mail": "judicious229757@companydomain.com",
      "groop": "CDN/Human resources",
      "number": "+74182598180"
    },
    {
      "id": 270,
      "FullName": "Derek Oman",
      "account": "companydomain/DerekOman",
      "mail": "jolly6175302@companydomain.com",
      "groop": "CDN/Top Kvants",
      "number": "+71003723433"
    },
    {
      "id": 271,
      "FullName": "Tanya Justice",
      "account": "companydomain/TanyaJustice",
      "mail": "barnacle4345471@companydomain.com",
      "groop": "CDN/Human resources",
      "number": "+78609381204"
    },
    {
      "id": 272,
      "FullName": "Sam Conklin",
      "account": "companydomain/SamConklin",
      "mail": "thankful1979564@companydomain.com",
      "groop": "CDN/Managers",
      "number": "+73538340859"
    },
    {
      "id": 273,
      "FullName": "Pedro Blakney",
      "account": "companydomain/PedroBlakney",
      "mail": "of8064004@companydomain.com",
      "groop": "CDN/Top Kvants",
      "number": "+73582590294"
    },
    {
      "id": 274,
      "FullName": "Richard Heenan",
      "account": "companydomain/RichardHeenan",
      "mail": "energetic1291587@companydomain.com",
      "groop": "CDN/Managers",
      "number": "+77455616230"
    },
    {
      "id": 275,
      "FullName": "Freddie Perez",
      "account": "companydomain/FreddiePerez",
      "mail": "bullfrog7917861@companydomain.com",
      "groop": "CDN/Sales",
      "number": "+75088093168"
    },
    {
      "id": 276,
      "FullName": "William Hobbs",
      "account": "companydomain/WilliamHobbs",
      "mail": "hedgehog3428519@companydomain.com",
      "groop": "CDN/CEO",
      "number": "+76705095450"
    },
    {
      "id": 277,
      "FullName": "Debra Curran",
      "account": "companydomain/DebraCurran",
      "mail": "prawn4669301@companydomain.com",
      "groop": "CDN/CEO",
      "number": "+71648852929"
    },
    {
      "id": 278,
      "FullName": "Samantha Corrales",
      "account": "companydomain/SamanthaCorrales",
      "mail": "sparrow5857364@companydomain.com",
      "groop": "CDN/Financials",
      "number": "+75760893213"
    },
    {
      "id": 279,
      "FullName": "Howard Beasley",
      "account": "companydomain/HowardBeasley",
      "mail": "smilodon10004@companydomain.com",
      "groop": "CDN/Managers",
      "number": "+74017240398"
    },
    {
      "id": 280,
      "FullName": "Carlton Sherman",
      "account": "companydomain/CarltonSherman",
      "mail": "of5288398@companydomain.com",
      "groop": "CDN/CEO",
      "number": "+76540959155"
    },
    {
      "id": 281,
      "FullName": "Callie Cordova",
      "account": "companydomain/CallieCordova",
      "mail": "charisma1414401@companydomain.com",
      "groop": "CDN/Top Kvants",
      "number": "+71132326386"
    },
    {
      "id": 282,
      "FullName": "Regina Thibeault",
      "account": "companydomain/ReginaThibeault",
      "mail": "eldorado8139870@companydomain.com",
      "groop": "CDN/Sales",
      "number": "+77029448976"
    },
    {
      "id": 283,
      "FullName": "David Klopfer",
      "account": "companydomain/DavidKlopfer",
      "mail": "karma1738736@companydomain.com",
      "groop": "Unmanaged",
      "number": "+73994779794"
    },
    {
      "id": 284,
      "FullName": "Valerie Brumbaugh",
      "account": "companydomain/ValerieBrumbaugh",
      "mail": "excitement576476@companydomain.com",
      "groop": "CDN/Financials",
      "number": "+76150472160"
    },
    {
      "id": 285,
      "FullName": "Anna Ferguson",
      "account": "companydomain/AnnaFerguson",
      "mail": "hawk4021025@companydomain.com",
      "groop": "CDN/Financials",
      "number": "+78638096062"
    },
    {
      "id": 286,
      "FullName": "Norma Dudley",
      "account": "companydomain/NormaDudley",
      "mail": "bullfrog9339439@companydomain.com",
      "groop": "CDN/Financials",
      "number": "+74171915596"
    },
    {
      "id": 287,
      "FullName": "Rebecca Chapa",
      "account": "companydomain/RebeccaChapa",
      "mail": "of8506615@companydomain.com",
      "groop": "Unmanaged",
      "number": "+74387146683"
    },
    {
      "id": 288,
      "FullName": "Beau Stout",
      "account": "companydomain/BeauStout",
      "mail": "drama3937796@companydomain.com",
      "groop": "CDN/Top Kvants",
      "number": "+74231195905"
    },
    {
      "id": 289,
      "FullName": "Pamela Jorgensen",
      "account": "companydomain/PamelaJorgensen",
      "mail": "of9999632@companydomain.com",
      "groop": "CDN/Top Kvants",
      "number": "+76091473675"
    },
    {
      "id": 290,
      "FullName": "Gloria Niemann",
      "account": "companydomain/GloriaNiemann",
      "mail": "of8229894@companydomain.com",
      "groop": "CDN/Managers",
      "number": "+71076067709"
    },
    {
      "id": 291,
      "FullName": "Viola Norman",
      "account": "companydomain/ViolaNorman",
      "mail": "of2728072@companydomain.com",
      "groop": "CDN/Human resources",
      "number": "+71531447268"
    },
    {
      "id": 292,
      "FullName": "Stephanie Shaffer",
      "account": "companydomain/StephanieShaffer",
      "mail": "spirited4480111@companydomain.com",
      "groop": "CDN/Financials",
      "number": "+75436986334"
    },
    {
      "id": 293,
      "FullName": "Allan Hawkins",
      "account": "companydomain/AllanHawkins",
      "mail": "vivacious5728676@companydomain.com",
      "groop": "CDN/Human resources",
      "number": "+72266308735"
    },
    {
      "id": 294,
      "FullName": "Doris Anderson",
      "account": "companydomain/DorisAnderson",
      "mail": "neat7346715@companydomain.com",
      "groop": "CDN/CEO",
      "number": "+77259690235"
    },
    {
      "id": 295,
      "FullName": "William Sherratt",
      "account": "companydomain/WilliamSherratt",
      "mail": "wolf5439149@companydomain.com",
      "groop": "CDN/CEO",
      "number": "+74048958656"
    },
    {
      "id": 296,
      "FullName": "Mary Adams",
      "account": "companydomain/MaryAdams",
      "mail": "enthusiasm2891355@companydomain.com",
      "groop": "CDN/Top Kvants",
      "number": "+78084766072"
    },
    {
      "id": 297,
      "FullName": "Philomena Mclaughlin",
      "account": "companydomain/PhilomenaMclaughlin",
      "mail": "husky6594545@companydomain.com",
      "groop": "CDN/Financials",
      "number": "+73603361577"
    },
    {
      "id": 298,
      "FullName": "Sheree Swift",
      "account": "companydomain/ShereeSwift",
      "mail": "mastery548437@companydomain.com",
      "groop": "CDN/Managers",
      "number": "+72258639039"
    },
    {
      "id": 299,
      "FullName": "Theresa Patterson",
      "account": "companydomain/TheresaPatterson",
      "mail": "gleaming6067891@companydomain.com",
      "groop": "Unmanaged",
      "number": "+79701299688"
    },
    {
      "id": 300,
      "FullName": "Vincent Jones",
      "account": "companydomain/VincentJones",
      "mail": "illegal8424312@companydomain.com",
      "groop": "CDN/Top Kvants",
      "number": "+79335814446"
    },
    {
      "id": 301,
      "FullName": "Donna Davis",
      "account": "companydomain/DonnaDavis",
      "mail": "butterfly2152992@companydomain.com",
      "groop": "CDN/Financials",
      "number": "+73799059211"
    },
    {
      "id": 302,
      "FullName": "Janice Cole",
      "account": "companydomain/JaniceCole",
      "mail": "economy3446400@companydomain.com",
      "groop": "CDN/Managers",
      "number": "+71242090383"
    },
    {
      "id": 303,
      "FullName": "Luis Ares",
      "account": "companydomain/LuisAres",
      "mail": "amethyst2122912@companydomain.com",
      "groop": "CDN/Human resources",
      "number": "+73499949183"
    },
    {
      "id": 304,
      "FullName": "William Flores",
      "account": "companydomain/WilliamFlores",
      "mail": "of9371387@companydomain.com",
      "groop": "Unmanaged",
      "number": "+77914300648"
    },
    {
      "id": 305,
      "FullName": "Margaret Sivels",
      "account": "companydomain/MargaretSivels",
      "mail": "realistic4233828@companydomain.com",
      "groop": "CDN/Sales",
      "number": "+71404167228"
    },
    {
      "id": 306,
      "FullName": "Anthony Leggett",
      "account": "companydomain/AnthonyLeggett",
      "mail": "secret2526450@companydomain.com",
      "groop": "CDN/Managers",
      "number": "+77895590599"
    },
    {
      "id": 307,
      "FullName": "Bobby Queen",
      "account": "companydomain/BobbyQueen",
      "mail": "debate5090531@companydomain.com",
      "groop": "CDN/CEO",
      "number": "+75233689214"
    },
    {
      "id": 308,
      "FullName": "Addie Martin",
      "account": "companydomain/AddieMartin",
      "mail": "tempest6567948@companydomain.com",
      "groop": "CDN/Top Kvants",
      "number": "+78405741648"
    },
    {
      "id": 309,
      "FullName": "Aurora Mack",
      "account": "companydomain/AuroraMack",
      "mail": "of8299454@companydomain.com",
      "groop": "CDN/Sales",
      "number": "+74828888021"
    },
    {
      "id": 310,
      "FullName": "Larry Rush",
      "account": "companydomain/LarryRush",
      "mail": "vigilant8492651@companydomain.com",
      "groop": "CDN/Financials",
      "number": "+78702473302"
    },
    {
      "id": 311,
      "FullName": "William Watts",
      "account": "companydomain/WilliamWatts",
      "mail": "impossible2287183@companydomain.com",
      "groop": "Unmanaged",
      "number": "+77673006373"
    },
    {
      "id": 312,
      "FullName": "Willis Hardin",
      "account": "companydomain/WillisHardin",
      "mail": "of5323221@companydomain.com",
      "groop": "CDN/Sales",
      "number": "+73813134757"
    },
    {
      "id": 313,
      "FullName": "Larry Earl",
      "account": "companydomain/LarryEarl",
      "mail": "of508458@companydomain.com",
      "groop": "CDN/Sales",
      "number": "+71206771740"
    },
    {
      "id": 314,
      "FullName": "Geri Smith",
      "account": "companydomain/GeriSmith",
      "mail": "tarantula559308@companydomain.com",
      "groop": "CDN/Managers",
      "number": "+79266084819"
    },
    {
      "id": 315,
      "FullName": "Geraldine Horky",
      "account": "companydomain/GeraldineHorky",
      "mail": "pristine9231363@companydomain.com",
      "groop": "Unmanaged",
      "number": "+73494735248"
    },
    {
      "id": 316,
      "FullName": "Maureen Phillips",
      "account": "companydomain/MaureenPhillips",
      "mail": "piety3231812@companydomain.com",
      "groop": "CDN/CEO",
      "number": "+77016684360"
    },
    {
      "id": 317,
      "FullName": "Barbara Hartley",
      "account": "companydomain/BarbaraHartley",
      "mail": "fast3069060@companydomain.com",
      "groop": "Unmanaged",
      "number": "+77563889338"
    },
    {
      "id": 318,
      "FullName": "Deborah Specht",
      "account": "companydomain/DeborahSpecht",
      "mail": "of1393981@companydomain.com",
      "groop": "CDN/Top Kvants",
      "number": "+71479981316"
    },
    {
      "id": 319,
      "FullName": "Allison Gloden",
      "account": "companydomain/AllisonGloden",
      "mail": "tarsier7710874@companydomain.com",
      "groop": "Unmanaged",
      "number": "+73258339030"
    },
    {
      "id": 320,
      "FullName": "Susan Todd",
      "account": "companydomain/SusanTodd",
      "mail": "thoughtful4904843@companydomain.com",
      "groop": "CDN/Financials",
      "number": "+77494705410"
    }
  ]
}